README.md
setup.py
tensorflow_transform/__init__.py
tensorflow_transform/analyzers.py
tensorflow_transform/analyzers_test.py
tensorflow_transform/api.py
tensorflow_transform/graph_tools.py
tensorflow_transform/graph_tools_test.py
tensorflow_transform/impl_helper.py
tensorflow_transform/impl_helper_test.py
tensorflow_transform/mappers.py
tensorflow_transform/mappers_test.py
tensorflow_transform/output_wrapper.py
tensorflow_transform/pretrained_models.py
tensorflow_transform/pretrained_models_test.py
tensorflow_transform/schema_inference.py
tensorflow_transform/schema_inference_test.py
tensorflow_transform/test_case.py
tensorflow_transform/test_case_test.py
tensorflow_transform/tf_utils.py
tensorflow_transform/tf_utils_test.py
tensorflow_transform/beam/__init__.py
tensorflow_transform/beam/analyzer_impls.py
tensorflow_transform/beam/analyzer_impls_test.py
tensorflow_transform/beam/common.py
tensorflow_transform/beam/deep_copy.py
tensorflow_transform/beam/deep_copy_test.py
tensorflow_transform/beam/impl.py
tensorflow_transform/beam/impl_test.py
tensorflow_transform/beam/shared.py
tensorflow_transform/beam/shared_test.py
tensorflow_transform/beam/tft_unit.py
tensorflow_transform/beam/tft_beam_io/__init__.py
tensorflow_transform/beam/tft_beam_io/beam_metadata_io.py
tensorflow_transform/beam/tft_beam_io/beam_metadata_io_test.py
tensorflow_transform/beam/tft_beam_io/transform_fn_io.py
tensorflow_transform/beam/tft_beam_io/transform_fn_io_test.py
tensorflow_transform/coders/__init__.py
tensorflow_transform/coders/csv_coder.py
tensorflow_transform/coders/csv_coder_test.py
tensorflow_transform/coders/example_proto_coder.py
tensorflow_transform/coders/example_proto_coder_test.py
tensorflow_transform/saved/__init__.py
tensorflow_transform/saved/constants.py
tensorflow_transform/saved/input_fn_maker.py
tensorflow_transform/saved/input_fn_maker_test.py
tensorflow_transform/saved/saved_model_loader.py
tensorflow_transform/saved/saved_model_loader_test.py
tensorflow_transform_canary.egg-info/PKG-INFO
tensorflow_transform_canary.egg-info/SOURCES.txt
tensorflow_transform_canary.egg-info/dependency_links.txt
tensorflow_transform_canary.egg-info/namespace_packages.txt
tensorflow_transform_canary.egg-info/requires.txt
tensorflow_transform_canary.egg-info/top_level.txt